dash_vega_components/Vega.py
dash_vega_components/__init__.py
dash_vega_components/_imports_.py
dash_vega_components/async-Vega.js
dash_vega_components/async-Vega.js.map
dash_vega_components/dash_vega_components.min.js
dash_vega_components/dash_vega_components.min.js.map
dash_vega_components/metadata.json
dash_vega_components/package-info.json
dash_vega_components-0.11.0.dist-info/LICENSE
dash_vega_components-0.11.0.dist-info/METADATA
dash_vega_components-0.11.0.dist-info/WHEEL
dash_vega_components-0.11.0.dist-info/top_level.txt
dash_vega_components-0.11.0.dist-info/RECORD
