Metadata-Version: 2.1
Name: dash-vega-components
Version: 0.11.0
Summary: Dash Vega Components
Author: Stefan Binder <binder_stefan@outlook.com>
License: BSD
Classifier: Framework :: Dash
License-File: LICENSE
